orrey/__init__.py
orrey/cli.py
orrey/model.py
orrey-0.0.1.dist-info/DESCRIPTION.rst
orrey-0.0.1.dist-info/METADATA
orrey-0.0.1.dist-info/RECORD
orrey-0.0.1.dist-info/WHEEL
orrey-0.0.1.dist-info/entry_points.txt
orrey-0.0.1.dist-info/metadata.json
orrey-0.0.1.dist-info/pbr.json
orrey-0.0.1.dist-info/top_level.txt
test/__init__.py
