Metadata-Version: 2.0
Name: orrey
Version: 0.0.1
Summary: Utilities for daily GLM tasks
Home-page: http://github.com/kastman/orrey
Author: Erik Kastman
Author-email: erik.kastman@gmail.com
License: GPL
Platform: UNKNOWN
Classifier: Development Status :: 1 - Planning
Classifier: License :: OSI Approved :: GNU General Public License v3 or later (GPLv3+)
Classifier: Programming Language :: Python
Classifier: Intended Audience :: Science/Research
Classifier: Topic :: Scientific/Engineering
Requires-Dist: moss
Requires-Dist: pandas
Requires-Dist: seaborn
